{
  "annotations": {
    "list": [
      {
        "builtIn": 1,
        "datasource": {
          "type": "prometheus",
          "uid": "${DS_PROMETHEUS}"
        },
        "enable": true,
        "hide": true,
        "iconColor": "rgba(0, 211, 255, 1)",
        "limit": 100,
        "name": "Annotations & Alerts",
        "showIn": 0,
        "target": {
          "limit": 100,
          "matchAny": false,
          "tags": [],
          "type": "dashboard"
        },
        "type": "dashboard"
      }
    ]
  },
  "description": "Logstash Health Monitoring: System, JVM, Pipeline and individual plugin stats for Logstash replicas running on Kubernetes.",
  "editable": true,
  "fiscalYearStartMonth": 0,
  "graphTooltip": 0,
  "id": 68,
  "links": [],
  "panels": [
    {
      "datasource": {
        "type": "prometheus",
        "uid": "${DS_PROMETHEUS}"
      },
      "description": "",
      "fieldConfig": {
        "defaults": {
          "color": {
            "mode": "palette-classic"
          },
          "mappings": [
            {
              "options": {
                "green": {
                  "color": "dark-green",
                  "index": 0
                },
                "red": {
                  "color": "dark-red",
                  "index": 1
                }
              },
              "type": "value"
            }
          ],
          "thresholds": {
            "mode": "absolute",
            "steps": [
              {
                "color": "transparent",
                "value": null
              }
            ]
          },
          "unit": "none"
        },
        "overrides": []
      },
      "gridPos": {
        "h": 7,
        "w": 12,
        "x": 0,
        "y": 0
      },
      "id": 6765,
      "options": {
        "colorMode": "background",
        "graphMode": "none",
        "justifyMode": "auto",
        "orientation": "auto",
        "percentChangeColorMode": "standard",
        "reduceOptions": {
          "calcs": [
            "lastNotNull"
          ],
          "fields": "/.*/",
          "values": false
        },
        "showPercentChange": false,
        "text": {},
        "textMode": "value_and_name",
        "wideLayout": true
      },
      "pluginVersion": "11.5.2",
      "targets": [
        {
          "datasource": {
            "type": "prometheus",
            "uid": "${DS_PROMETHEUS}"
          },
          "editorMode": "code",
          "exemplar": false,
          "expr": "count(logstash_info_node)",
          "format": "heatmap",
          "instant": true,
          "legendFormat": "logstash instances",
          "range": false,
          "refId": "A"
        },
        {
          "datasource": {
            "type": "prometheus",
            "uid": "${DS_PROMETHEUS}"
          },
          "editorMode": "code",
          "exemplar": false,
          "expr": "max (sum by (instance) (logstash_stats_pipeline_up))",
          "format": "heatmap",
          "hide": false,
          "instant": true,
          "legendFormat": "Total number of Pipeline (per instance)",
          "range": false,
          "refId": "B"
        }
      ],
      "title": "Deployed Chart Version by Instance",
      "transformations": [
        {
          "id": "organize",
          "options": {
            "excludeByName": {
              "Time": true,
              "Value": true,
              "pod": false
            },
            "indexByName": {
              "Time": 0,
              "Value": 4,
              "pod": 1,
              "status": 2,
              "version": 3
            },
            "renameByName": {
              "Time": "",
              "Value": "",
              "pod": "Replica",
              "status": "Replica Status",
              "version": "Helm Version"
            }
          }
        },
        {
          "id": "sortBy",
          "options": {
            "fields": {},
            "sort": [
              {
                "field": "Replica"
              }
            ]
          }
        },
        {
          "id": "rowsToFields",
          "options": {
            "mappings": [
              {
                "fieldName": "Helm Deployment Version",
                "handlerKey": "field.value"
              },
              {
                "fieldName": "Replica Status",
                "handlerKey": "color"
              },
              {
                "fieldName": "Replica",
                "handlerKey": "field.name"
              },
              {
                "fieldName": "Helm Version",
                "handlerKey": "field.value"
              }
            ]
          }
        }
      ],
      "type": "stat"
    },
    {
      "datasource": {
        "type": "prometheus",
        "uid": "${DS_PROMETHEUS}"
      },
      "fieldConfig": {
        "defaults": {
          "color": {
            "mode": "thresholds"
          },
          "decimals": 0,
          "mappings": [],
          "thresholds": {
            "mode": "absolute",
            "steps": [
              {
                "color": "green",
                "value": null
              }
            ]
          },
          "unit": "locale"
        },
        "overrides": [
          {
            "matcher": {
              "id": "byName",
              "options": "OUT"
            },
            "properties": [
              {
                "id": "color",
                "value": {
                  "fixedColor": "purple",
                  "mode": "fixed"
                }
              }
            ]
          }
        ]
      },
      "gridPos": {
        "h": 7,
        "w": 12,
        "x": 12,
        "y": 0
      },
      "id": 6897,
      "options": {
        "colorMode": "value",
        "graphMode": "area",
        "justifyMode": "auto",
        "orientation": "auto",
        "percentChangeColorMode": "standard",
        "reduceOptions": {
          "calcs": [
            "lastNotNull"
          ],
          "fields": "",
          "values": false
        },
        "showPercentChange": false,
        "textMode": "auto",
        "wideLayout": true
      },
      "pluginVersion": "11.5.2",
      "targets": [
        {
          "datasource": {
            "type": "prometheus",
            "uid": "${DS_PROMETHEUS}"
          },
          "editorMode": "code",
          "expr": "sum(increase(logstash_stats_pipeline_events_in{instance=~'$instance',pipeline=~'$pipeline'}[$__range]))",
          "legendFormat": "IN",
          "range": true,
          "refId": "A"
        },
        {
          "datasource": {
            "type": "prometheus",
            "uid": "${DS_PROMETHEUS}"
          },
          "editorMode": "code",
          "expr": "sum(increase(logstash_stats_pipeline_events_out{instance=~'$instance',pipeline=~'$pipeline'}[$__range]))",
          "hide": false,
          "legendFormat": "OUT",
          "range": true,
          "refId": "B"
        }
      ],
      "title": "Total Events In/Out",
      "transparent": true,
      "type": "stat"
    },
    {
      "collapsed": false,
      "gridPos": {
        "h": 1,
        "w": 24,
        "x": 0,
        "y": 7
      },
      "id": 6793,
      "panels": [],
      "title": "Status Overview",
      "type": "row"
    },
    {
      "datasource": {
        "type": "prometheus",
        "uid": "${DS_PROMETHEUS}"
      },
      "fieldConfig": {
        "defaults": {
          "color": {
            "mode": "thresholds"
          },
          "mappings": [
            {
              "options": {
                "0": {
                  "color": "dark-red",
                  "index": 0,
                  "text": "Down"
                },
                "1": {
                  "color": "green",
                  "index": 1,
                  "text": "Up"
                }
              },
              "type": "value"
            },
            {
              "options": {
                "match": "null+nan",
                "result": {
                  "color": "#72946d",
                  "index": 2,
                  "text": "–"
                }
              },
              "type": "special"
            }
          ],
          "thresholds": {
            "mode": "absolute",
            "steps": [
              {
                "color": "dark-green",
                "value": null
              }
            ]
          },
          "unit": "iops"
        },
        "overrides": []
      },
      "gridPos": {
        "h": 11,
        "w": 12,
        "x": 0,
        "y": 8
      },
      "id": 6775,
      "options": {
        "colorMode": "background",
        "graphMode": "area",
        "justifyMode": "auto",
        "orientation": "auto",
        "percentChangeColorMode": "standard",
        "reduceOptions": {
          "calcs": [
            "lastNotNull"
          ],
          "fields": "",
          "values": false
        },
        "showPercentChange": false,
        "text": {},
        "textMode": "value_and_name",
        "wideLayout": true
      },
      "pluginVersion": "11.5.2",
      "targets": [
        {
          "datasource": {
            "type": "prometheus",
            "uid": "${DS_PROMETHEUS}"
          },
          "editorMode": "code",
          "exemplar": false,
          "expr": "max(rate(logstash_stats_pipeline_events_out{instance=~'$instance',pipeline=~\"$pipeline\"}[$__range]) / rate(logstash_stats_pipeline_events_duration{instance=~'$instance',pipeline=~\"$pipeline\"}[$__range])*1000 > 0) by (pipeline) or max(logstash_stats_pipeline_up{}) by (pipeline)",
          "format": "table",
          "hide": false,
          "instant": true,
          "legendFormat": "{{rate}}",
          "range": false,
          "refId": "rate"
        }
      ],
      "title": "Pipeline Status + Max Rate Last Hour",
      "transformations": [
        {
          "id": "seriesToColumns",
          "options": {
            "byField": "pipeline"
          }
        },
        {
          "id": "sortBy",
          "options": {
            "fields": {},
            "sort": [
              {
                "field": "pipeline"
              }
            ]
          }
        },
        {
          "id": "rowsToFields",
          "options": {
            "mappings": [
              {
                "fieldName": "pipeline",
                "handlerKey": "field.name"
              },
              {
                "fieldName": "Time 1",
                "handlerKey": "__ignore"
              },
              {
                "fieldName": "Value #status",
                "handlerKey": "mappings.color"
              },
              {
                "fieldName": "Time 2",
                "handlerKey": "__ignore"
              },
              {
                "fieldName": "Value #rate",
                "handlerKey": "__ignore"
              },
              {
                "fieldName": "Value",
                "handlerKey": "field.value"
              },
              {
                "fieldName": "Time",
                "handlerKey": "__ignore"
              }
            ]
          }
        }
      ],
      "type": "stat"
    },
    {
      "datasource": {
        "type": "prometheus",
        "uid": "${DS_PROMETHEUS}"
      },
      "description": "Successful Writes to Elasticsearch/OpenSearch",
      "fieldConfig": {
        "defaults": {
          "color": {
            "mode": "palette-classic"
          },
          "custom": {
            "axisBorderShow": false,
            "axisCenteredZero": false,
            "axisColorMode": "text",
            "axisLabel": "",
            "axisPlacement": "auto",
            "barAlignment": 0,
            "barWidthFactor": 0.6,
            "drawStyle": "line",
            "fillOpacity": 0,
            "gradientMode": "none",
            "hideFrom": {
              "legend": false,
              "tooltip": false,
              "viz": false
            },
            "insertNulls": false,
            "lineInterpolation": "linear",
            "lineWidth": 1,
            "pointSize": 5,
            "scaleDistribution": {
              "type": "linear"
            },
            "showPoints": "auto",
            "spanNulls": false,
            "stacking": {
              "group": "A",
              "mode": "none"
            },
            "thresholdsStyle": {
              "mode": "off"
            }
          },
          "mappings": [
            {
              "options": {
                "NaN": {
                  "index": 0,
                  "text": "Nodata"
                }
              },
              "type": "value"
            }
          ],
          "thresholds": {
            "mode": "absolute",
            "steps": [
              {
                "color": "green",
                "value": null
              }
            ]
          },
          "unit": "percent"
        },
        "overrides": []
      },
      "gridPos": {
        "h": 11,
        "w": 12,
        "x": 12,
        "y": 8
      },
      "id": 6919,
      "options": {
        "legend": {
          "calcs": [],
          "displayMode": "list",
          "placement": "bottom",
          "showLegend": true
        },
        "tooltip": {
          "hideZeros": false,
          "maxHeight": 600,
          "mode": "single",
          "sort": "none"
        }
      },
      "pluginVersion": "11.5.2",
      "targets": [
        {
          "datasource": {
            "type": "prometheus",
            "uid": "${DS_PROMETHEUS}"
          },
          "editorMode": "code",
          "expr": "(sum by (pipeline) (logstash_stats_pipeline_plugin_documents_successes{plugin!=\"stdout\"}) / ((sum by (pipeline) (logstash_stats_pipeline_plugin_documents_successes{plugin!=\"stdout\"})) + (sum by (pipeline) (logstash_stats_pipeline_plugin_documents_non_retryable_failures{plugin!=\"stdout\"}))) *100) ",
          "legendFormat": "{{pipeline}}",
          "range": true,
          "refId": "A"
        }
      ],
      "title": "Output Write Successes Rate (%)",
      "transformations": [
        {
          "disabled": true,
          "id": "rowsToFields",
          "options": {}
        }
      ],
      "transparent": true,
      "type": "timeseries"
    },
    {
      "collapsed": false,
      "gridPos": {
        "h": 1,
        "w": 24,
        "x": 0,
        "y": 19
      },
      "id": 6763,
      "panels": [],
      "title": "System Load Averages by Instance",
      "type": "row"
    },
    {
      "datasource": {
        "type": "prometheus",
        "uid": "${DS_PROMETHEUS}"
      },
      "description": "Processes using or waiting for CPU",
      "fieldConfig": {
        "defaults": {
          "color": {
            "mode": "palette-classic"
          },
          "custom": {
            "axisBorderShow": false,
            "axisCenteredZero": false,
            "axisColorMode": "text",
            "axisLabel": "",
            "axisPlacement": "auto",
            "barAlignment": 0,
            "barWidthFactor": 0.6,
            "drawStyle": "line",
            "fillOpacity": 25,
            "gradientMode": "none",
            "hideFrom": {
              "legend": false,
              "tooltip": false,
              "viz": false
            },
            "insertNulls": false,
            "lineInterpolation": "linear",
            "lineWidth": 1,
            "pointSize": 5,
            "scaleDistribution": {
              "type": "linear"
            },
            "showPoints": "auto",
            "spanNulls": false,
            "stacking": {
              "group": "A",
              "mode": "none"
            },
            "thresholdsStyle": {
              "mode": "line+area"
            }
          },
          "mappings": [],
          "thresholds": {
            "mode": "absolute",
            "steps": [
              {
                "color": "green",
                "value": null
              },
              {
                "color": "dark-red",
                "value": 1
              }
            ]
          }
        },
        "overrides": [
          {
            "matcher": {
              "id": "byName",
              "options": "1 min"
            },
            "properties": [
              {
                "id": "color",
                "value": {
                  "fixedColor": "dark-green",
                  "mode": "fixed"
                }
              }
            ]
          },
          {
            "matcher": {
              "id": "byName",
              "options": "5 min"
            },
            "properties": [
              {
                "id": "color",
                "value": {
                  "fixedColor": "dark-yellow",
                  "mode": "fixed"
                }
              }
            ]
          },
          {
            "matcher": {
              "id": "byName",
              "options": "15 min"
            },
            "properties": [
              {
                "id": "color",
                "value": {
                  "fixedColor": "blue",
                  "mode": "fixed"
                }
              }
            ]
          },
          {
            "__systemRef": "hideSeriesFrom",
            "matcher": {
              "id": "byNames",
              "options": {
                "mode": "exclude",
                "names": [
                  "leader10:9198"
                ],
                "prefix": "All except:",
                "readOnly": true
              }
            },
            "properties": [
              {
                "id": "custom.hideFrom",
                "value": {
                  "legend": false,
                  "tooltip": false,
                  "viz": false
                }
              }
            ]
          }
        ]
      },
      "gridPos": {
        "h": 9,
        "w": 12,
        "x": 0,
        "y": 20
      },
      "id": 2461,
      "maxPerRow": 3,
      "options": {
        "legend": {
          "calcs": [],
          "displayMode": "list",
          "placement": "bottom",
          "showLegend": true
        },
        "tooltip": {
          "hideZeros": false,
          "maxHeight": 600,
          "mode": "single",
          "sort": "asc"
        }
      },
      "pluginVersion": "11.5.2",
      "targets": [
        {
          "datasource": {
            "type": "prometheus",
            "uid": "${DS_PROMETHEUS}"
          },
          "editorMode": "code",
          "exemplar": false,
          "expr": "logstash_stats_process_cpu_load_average_15m{instance=~'$instance'}",
          "instant": false,
          "legendFormat": "{{instance}}",
          "range": true,
          "refId": "A"
        }
      ],
      "title": "System Load Average in 15m ($instance) ",
      "transformations": [
        {
          "id": "configFromData",
          "options": {}
        }
      ],
      "transparent": true,
      "type": "timeseries"
    },
    {
      "datasource": {
        "type": "prometheus",
        "uid": "${DS_PROMETHEUS}"
      },
      "description": "Processes using or waiting for CPU",
      "fieldConfig": {
        "defaults": {
          "color": {
            "mode": "palette-classic"
          },
          "custom": {
            "axisBorderShow": false,
            "axisCenteredZero": false,
            "axisColorMode": "text",
            "axisLabel": "",
            "axisPlacement": "auto",
            "barAlignment": 0,
            "barWidthFactor": 0.6,
            "drawStyle": "line",
            "fillOpacity": 25,
            "gradientMode": "none",
            "hideFrom": {
              "legend": false,
              "tooltip": false,
              "viz": false
            },
            "insertNulls": false,
            "lineInterpolation": "linear",
            "lineWidth": 1,
            "pointSize": 5,
            "scaleDistribution": {
              "type": "linear"
            },
            "showPoints": "auto",
            "spanNulls": false,
            "stacking": {
              "group": "A",
              "mode": "none"
            },
            "thresholdsStyle": {
              "mode": "line+area"
            }
          },
          "mappings": [],
          "thresholds": {
            "mode": "absolute",
            "steps": [
              {
                "color": "green",
                "value": null
              },
              {
                "color": "dark-red",
                "value": 1
              }
            ]
          }
        },
        "overrides": [
          {
            "matcher": {
              "id": "byName",
              "options": "1 min"
            },
            "properties": [
              {
                "id": "color",
                "value": {
                  "fixedColor": "dark-green",
                  "mode": "fixed"
                }
              }
            ]
          },
          {
            "matcher": {
              "id": "byName",
              "options": "5 min"
            },
            "properties": [
              {
                "id": "color",
                "value": {
                  "fixedColor": "dark-yellow",
                  "mode": "fixed"
                }
              }
            ]
          },
          {
            "matcher": {
              "id": "byName",
              "options": "15 min"
            },
            "properties": [
              {
                "id": "color",
                "value": {
                  "fixedColor": "blue",
                  "mode": "fixed"
                }
              }
            ]
          },
          {
            "__systemRef": "hideSeriesFrom",
            "matcher": {
              "id": "byNames",
              "options": {
                "mode": "exclude",
                "names": [
                  "leader10:9198"
                ],
                "prefix": "All except:",
                "readOnly": true
              }
            },
            "properties": [
              {
                "id": "custom.hideFrom",
                "value": {
                  "legend": false,
                  "tooltip": false,
                  "viz": false
                }
              }
            ]
          }
        ]
      },
      "gridPos": {
        "h": 9,
        "w": 12,
        "x": 12,
        "y": 20
      },
      "id": 7221,
      "maxPerRow": 3,
      "options": {
        "legend": {
          "calcs": [],
          "displayMode": "list",
          "placement": "bottom",
          "showLegend": true
        },
        "tooltip": {
          "hideZeros": false,
          "maxHeight": 600,
          "mode": "single",
          "sort": "asc"
        }
      },
      "pluginVersion": "11.5.2",
      "targets": [
        {
          "datasource": {
            "type": "prometheus",
            "uid": "${DS_PROMETHEUS}"
          },
          "editorMode": "code",
          "exemplar": false,
          "expr": "logstash_stats_process_cpu_load_average_5m{instance=~'$instance'}",
          "instant": false,
          "legendFormat": "{{instance}}",
          "range": true,
          "refId": "A"
        }
      ],
      "title": "System Load Average in 5m ($instance)",
      "transformations": [
        {
          "id": "configFromData",
          "options": {}
        }
      ],
      "transparent": true,
      "type": "timeseries"
    },
    {
      "collapsed": false,
      "gridPos": {
        "h": 1,
        "w": 24,
        "x": 0,
        "y": 29
      },
      "id": 2459,
      "panels": [],
      "title": "Process Metrics (All Selected Instance)",
      "type": "row"
    },
    {
      "datasource": {
        "type": "prometheus",
        "uid": "${DS_PROMETHEUS}"
      },
      "description": "",
      "fieldConfig": {
        "defaults": {
          "color": {
            "mode": "palette-classic"
          },
          "custom": {
            "axisBorderShow": false,
            "axisCenteredZero": false,
            "axisColorMode": "text",
            "axisLabel": "",
            "axisPlacement": "auto",
            "barAlignment": 0,
            "barWidthFactor": 0.6,
            "drawStyle": "line",
            "fillOpacity": 9,
            "gradientMode": "hue",
            "hideFrom": {
              "legend": false,
              "tooltip": false,
              "viz": false
            },
            "insertNulls": false,
            "lineInterpolation": "smooth",
            "lineWidth": 1,
            "pointSize": 5,
            "scaleDistribution": {
              "type": "linear"
            },
            "showPoints": "auto",
            "spanNulls": false,
            "stacking": {
              "group": "A",
              "mode": "none"
            },
            "thresholdsStyle": {
              "mode": "off"
            }
          },
          "mappings": [],
          "thresholds": {
            "mode": "absolute",
            "steps": [
              {
                "color": "green",
                "value": null
              },
              {
                "color": "red",
                "value": 80
              }
            ]
          },
          "unit": "percent"
        },
        "overrides": []
      },
      "gridPos": {
        "h": 6,
        "w": 24,
        "x": 0,
        "y": 30
      },
      "id": 6747,
      "options": {
        "legend": {
          "calcs": [],
          "displayMode": "list",
          "placement": "right",
          "showLegend": true
        },
        "tooltip": {
          "hideZeros": false,
          "maxHeight": 600,
          "mode": "single",
          "sort": "none"
        }
      },
      "pluginVersion": "11.5.2",
      "targets": [
        {
          "datasource": {
            "type": "prometheus",
            "uid": "${DS_PROMETHEUS}"
          },
          "editorMode": "code",
          "exemplar": true,
          "expr": "logstash_stats_process_cpu_percent{instance=~'$instance'}",
          "format": "time_series",
          "instant": false,
          "legendFormat": "cpu_pct ({{instance}})",
          "range": true,
          "refId": "A"
        }
      ],
      "title": "CPU Utilization %",
      "type": "timeseries"
    },
    {
      "datasource": {
        "type": "prometheus",
        "uid": "${DS_PROMETHEUS}"
      },
      "fieldConfig": {
        "defaults": {
          "color": {
            "mode": "palette-classic"
          },
          "custom": {
            "axisBorderShow": false,
            "axisCenteredZero": false,
            "axisColorMode": "text",
            "axisLabel": "",
            "axisPlacement": "auto",
            "barAlignment": 0,
            "barWidthFactor": 0.6,
            "drawStyle": "line",
            "fillOpacity": 10,
            "gradientMode": "none",
            "hideFrom": {
              "legend": false,
              "tooltip": false,
              "viz": false
            },
            "insertNulls": false,
            "lineInterpolation": "linear",
            "lineWidth": 1,
            "pointSize": 5,
            "scaleDistribution": {
              "type": "linear"
            },
            "showPoints": "never",
            "spanNulls": true,
            "stacking": {
              "group": "A",
              "mode": "none"
            },
            "thresholdsStyle": {
              "mode": "off"
            }
          },
          "links": [],
          "mappings": [],
          "thresholds": {
            "mode": "absolute",
            "steps": [
              {
                "color": "green",
                "value": null
              },
              {
                "color": "red",
                "value": 80
              }
            ]
          },
          "unit": "decbytes"
        },
        "overrides": []
      },
      "gridPos": {
        "h": 6,
        "w": 24,
        "x": 0,
        "y": 36
      },
      "id": 2464,
      "options": {
        "legend": {
          "calcs": [
            "mean",
            "max"
          ],
          "displayMode": "table",
          "placement": "right",
          "showLegend": true
        },
        "tooltip": {
          "hideZeros": false,
          "maxHeight": 600,
          "mode": "multi",
          "sort": "none"
        }
      },
      "pluginVersion": "11.5.2",
      "targets": [
        {
          "datasource": {
            "type": "prometheus",
            "uid": "${DS_PROMETHEUS}"
          },
          "editorMode": "code",
          "exemplar": true,
          "expr": "logstash_stats_process_mem_total_virtual{instance=~'$instance'}",
          "format": "time_series",
          "instant": false,
          "legendFormat": "vmem ({{instance}})",
          "range": true,
          "refId": "A"
        }
      ],
      "title": "Logstash Process Total Virtual Memory",
      "transparent": true,
      "type": "timeseries"
    },
    {
      "datasource": {
        "type": "prometheus",
        "uid": "${DS_PROMETHEUS}"
      },
      "fieldConfig": {
        "defaults": {
          "color": {
            "mode": "palette-classic"
          },
          "custom": {
            "axisBorderShow": false,
            "axisCenteredZero": false,
            "axisColorMode": "text",
            "axisLabel": "",
            "axisPlacement": "auto",
            "barAlignment": 0,
            "barWidthFactor": 0.6,
            "drawStyle": "line",
            "fillOpacity": 10,
            "gradientMode": "none",
            "hideFrom": {
              "legend": false,
              "tooltip": false,
              "viz": false
            },
            "insertNulls": false,
            "lineInterpolation": "linear",
            "lineWidth": 1,
            "pointSize": 5,
            "scaleDistribution": {
              "log": 10,
              "type": "log"
            },
            "showPoints": "never",
            "spanNulls": true,
            "stacking": {
              "group": "A",
              "mode": "none"
            },
            "thresholdsStyle": {
              "mode": "off"
            }
          },
          "links": [],
          "mappings": [],
          "thresholds": {
            "mode": "absolute",
            "steps": [
              {
                "color": "green",
                "value": null
              },
              {
                "color": "red",
                "value": 80
              }
            ]
          },
          "unit": "percent"
        },
        "overrides": []
      },
      "gridPos": {
        "h": 6,
        "w": 24,
        "x": 0,
        "y": 42
      },
      "id": 2463,
      "options": {
        "legend": {
          "calcs": [],
          "displayMode": "table",
          "placement": "right",
          "showLegend": true
        },
        "tooltip": {
          "hideZeros": false,
          "maxHeight": 600,
          "mode": "multi",
          "sort": "none"
        }
      },
      "pluginVersion": "11.5.2",
      "targets": [
        {
          "datasource": {
            "type": "prometheus",
            "uid": "${DS_PROMETHEUS}"
          },
          "editorMode": "code",
          "exemplar": true,
          "expr": "logstash_stats_process_open_file_descriptors{instance=~'$instance'} / logstash_stats_process_max_file_descriptors{instance=~'$instance'} *100",
          "hide": false,
          "legendFormat": "percent_open_fds ({{instance}}) ",
          "range": true,
          "refId": "A"
        },
        {
          "datasource": {
            "type": "prometheus",
            "uid": "${DS_PROMETHEUS}"
          },
          "editorMode": "code",
          "exemplar": true,
          "expr": "logstash_stats_process_open_file_descriptors{instance=~'$instance'}",
          "hide": true,
          "legendFormat": "open_fds ({{instance}})",
          "range": true,
          "refId": "B"
        }
      ],
      "title": "Logstash Open FIle Descriptors %",
      "transparent": true,
      "type": "timeseries"
    },
    {
      "collapsed": false,
      "gridPos": {
        "h": 1,
        "w": 24,
        "x": 0,
        "y": 48
      },
      "id": 953,
      "panels": [],
      "title": "JVM  (All Selected Instances)",
      "type": "row"
    },
    {
      "datasource": {
        "type": "prometheus",
        "uid": "${DS_PROMETHEUS}"
      },
      "fieldConfig": {
        "defaults": {
          "color": {
            "mode": "palette-classic"
          },
          "custom": {
            "axisBorderShow": false,
            "axisCenteredZero": false,
            "axisColorMode": "text",
            "axisLabel": "",
            "axisPlacement": "auto",
            "barAlignment": 0,
            "barWidthFactor": 0.6,
            "drawStyle": "line",
            "fillOpacity": 10,
            "gradientMode": "none",
            "hideFrom": {
              "legend": false,
              "tooltip": false,
              "viz": false
            },
            "insertNulls": false,
            "lineInterpolation": "linear",
            "lineWidth": 1,
            "pointSize": 5,
            "scaleDistribution": {
              "type": "linear"
            },
            "showPoints": "never",
            "spanNulls": false,
            "stacking": {
              "group": "A",
              "mode": "none"
            },
            "thresholdsStyle": {
              "mode": "off"
            }
          },
          "links": [],
          "mappings": [],
          "thresholds": {
            "mode": "absolute",
            "steps": [
              {
                "color": "green",
                "value": null
              },
              {
                "color": "red",
                "value": 80
              }
            ]
          },
          "unit": "percent"
        },
        "overrides": []
      },
      "gridPos": {
        "h": 6,
        "w": 24,
        "x": 0,
        "y": 49
      },
      "id": 1599,
      "options": {
        "legend": {
          "calcs": [
            "lastNotNull",
            "max"
          ],
          "displayMode": "table",
          "placement": "right",
          "showLegend": true
        },
        "tooltip": {
          "hideZeros": false,
          "maxHeight": 600,
          "mode": "multi",
          "sort": "none"
        }
      },
      "pluginVersion": "11.5.2",
      "targets": [
        {
          "datasource": {
            "type": "prometheus",
            "uid": "${DS_PROMETHEUS}"
          },
          "editorMode": "code",
          "expr": "logstash_stats_jvm_mem_heap_used_percent{instance=~'$instance'}",
          "legendFormat": "{{instance}}-jvm-usage",
          "range": true,
          "refId": "A"
        }
      ],
      "title": "JVM Heap % used",
      "transparent": true,
      "type": "timeseries"
    },
    {
      "datasource": {
        "type": "prometheus",
        "uid": "${DS_PROMETHEUS}"
      },
      "fieldConfig": {
        "defaults": {
          "color": {
            "mode": "palette-classic"
          },
          "custom": {
            "axisBorderShow": false,
            "axisCenteredZero": false,
            "axisColorMode": "text",
            "axisLabel": "",
            "axisPlacement": "auto",
            "barAlignment": 0,
            "barWidthFactor": 0.6,
            "drawStyle": "line",
            "fillOpacity": 0,
            "gradientMode": "none",
            "hideFrom": {
              "legend": false,
              "tooltip": false,
              "viz": false
            },
            "insertNulls": false,
            "lineInterpolation": "linear",
            "lineWidth": 1,
            "pointSize": 5,
            "scaleDistribution": {
              "type": "linear"
            },
            "showPoints": "never",
            "spanNulls": false,
            "stacking": {
              "group": "A",
              "mode": "none"
            },
            "thresholdsStyle": {
              "mode": "line"
            }
          },
          "links": [],
          "mappings": [],
          "thresholds": {
            "mode": "absolute",
            "steps": [
              {
                "color": "green",
                "value": null
              }
            ]
          },
          "unit": "bytes"
        },
        "overrides": []
      },
      "gridPos": {
        "h": 6,
        "w": 24,
        "x": 0,
        "y": 55
      },
      "id": 1435,
      "options": {
        "legend": {
          "calcs": [
            "lastNotNull"
          ],
          "displayMode": "table",
          "placement": "right",
          "showLegend": true
        },
        "tooltip": {
          "hideZeros": false,
          "maxHeight": 600,
          "mode": "multi",
          "sort": "none"
        }
      },
      "pluginVersion": "11.5.2",
      "targets": [
        {
          "datasource": {
            "type": "prometheus",
            "uid": "${DS_PROMETHEUS}"
          },
          "editorMode": "code",
          "exemplar": true,
          "expr": "logstash_stats_jvm_mem_heap_used_bytes{instance=~'$instance'}",
          "hide": false,
          "legendFormat": "{{instance}}-jvm-used",
          "range": true,
          "refId": "B"
        },
        {
          "datasource": {
            "type": "prometheus",
            "uid": "${DS_PROMETHEUS}"
          },
          "editorMode": "code",
          "exemplar": true,
          "expr": "logstash_stats_jvm_mem_heap_max_bytes{instance=~'$instance'}",
          "hide": false,
          "legendFormat": "{{instance}}-jvm-max",
          "range": true,
          "refId": "A"
        }
      ],
      "title": "JVM Heap usage",
      "transparent": true,
      "type": "timeseries"
    },
    {
      "datasource": {
        "type": "prometheus",
        "uid": "${DS_PROMETHEUS}"
      },
      "fieldConfig": {
        "defaults": {
          "color": {
            "mode": "palette-classic"
          },
          "custom": {
            "axisBorderShow": false,
            "axisCenteredZero": false,
            "axisColorMode": "text",
            "axisLabel": "",
            "axisPlacement": "auto",
            "barAlignment": 0,
            "barWidthFactor": 0.6,
            "drawStyle": "line",
            "fillOpacity": 10,
            "gradientMode": "none",
            "hideFrom": {
              "legend": false,
              "tooltip": false,
              "viz": false
            },
            "insertNulls": false,
            "lineInterpolation": "linear",
            "lineWidth": 1,
            "pointSize": 5,
            "scaleDistribution": {
              "type": "linear"
            },
            "showPoints": "never",
            "spanNulls": false,
            "stacking": {
              "group": "A",
              "mode": "none"
            },
            "thresholdsStyle": {
              "mode": "off"
            }
          },
          "links": [],
          "mappings": [],
          "thresholds": {
            "mode": "absolute",
            "steps": [
              {
                "color": "green",
                "value": null
              },
              {
                "color": "red",
                "value": 80
              }
            ]
          },
          "unit": "short"
        },
        "overrides": []
      },
      "gridPos": {
        "h": 6,
        "w": 24,
        "x": 0,
        "y": 61
      },
      "id": 2127,
      "options": {
        "legend": {
          "calcs": [],
          "displayMode": "table",
          "placement": "right",
          "showLegend": true
        },
        "tooltip": {
          "hideZeros": false,
          "maxHeight": 600,
          "mode": "multi",
          "sort": "none"
        }
      },
      "pluginVersion": "11.5.2",
      "targets": [
        {
          "datasource": {
            "type": "prometheus",
            "uid": "${DS_PROMETHEUS}"
          },
          "editorMode": "code",
          "exemplar": true,
          "expr": "logstash_stats_jvm_threads_count{instance=~'$instance'}",
          "hide": false,
          "legendFormat": "{{instance}}-threads_count",
          "range": true,
          "refId": "A"
        },
        {
          "datasource": {
            "type": "prometheus",
            "uid": "${DS_PROMETHEUS}"
          },
          "editorMode": "code",
          "exemplar": true,
          "expr": "logstash_stats_jvm_threads_peak_count{instance=~'$instance'}",
          "legendFormat": "{{instance}}-threads_peak",
          "range": true,
          "refId": "B"
        }
      ],
      "title": "Threads count",
      "transparent": true,
      "type": "timeseries"
    },
    {
      "datasource": {
        "type": "prometheus",
        "uid": "${DS_PROMETHEUS}"
      },
      "fieldConfig": {
        "defaults": {
          "color": {
            "mode": "palette-classic"
          },
          "custom": {
            "axisBorderShow": false,
            "axisCenteredZero": false,
            "axisColorMode": "text",
            "axisLabel": "",
            "axisPlacement": "auto",
            "barAlignment": 0,
            "barWidthFactor": 0.6,
            "drawStyle": "line",
            "fillOpacity": 0,
            "gradientMode": "none",
            "hideFrom": {
              "legend": false,
              "tooltip": false,
              "viz": false
            },
            "insertNulls": false,
            "lineInterpolation": "linear",
            "lineWidth": 1,
            "pointSize": 5,
            "scaleDistribution": {
              "type": "linear"
            },
            "showPoints": "never",
            "spanNulls": false,
            "stacking": {
              "group": "A",
              "mode": "none"
            },
            "thresholdsStyle": {
              "mode": "off"
            }
          },
          "links": [],
          "mappings": [],
          "thresholds": {
            "mode": "absolute",
            "steps": [
              {
                "color": "green",
                "value": null
              },
              {
                "color": "red",
                "value": 80
              }
            ]
          },
          "unit": "decbytes"
        },
        "overrides": []
      },
      "gridPos": {
        "h": 6,
        "w": 8,
        "x": 0,
        "y": 67
      },
      "id": 2287,
      "options": {
        "legend": {
          "calcs": [],
          "displayMode": "list",
          "placement": "bottom",
          "showLegend": false
        },
        "tooltip": {
          "hideZeros": false,
          "maxHeight": 600,
          "mode": "multi",
          "sort": "none"
        }
      },
      "pluginVersion": "11.5.2",
      "targets": [
        {
          "datasource": {
            "type": "prometheus",
            "uid": "${DS_PROMETHEUS}"
          },
          "editorMode": "code",
          "exemplar": true,
          "expr": "logstash_stats_jvm_mem_pool_committed_bytes{pool='young',instance=~'$instance'}",
          "legendFormat": "young_pool_committed ({{instance}})",
          "range": true,
          "refId": "A"
        },
        {
          "datasource": {
            "type": "prometheus",
            "uid": "${DS_PROMETHEUS}"
          },
          "editorMode": "code",
          "exemplar": true,
          "expr": "logstash_stats_jvm_mem_pool_max_bytes{pool='young',instance=~'$instance'}",
          "hide": false,
          "legendFormat": "\"young_pool_max  ({{instance}})",
          "range": true,
          "refId": "B"
        },
        {
          "datasource": {
            "type": "prometheus",
            "uid": "${DS_PROMETHEUS}"
          },
          "editorMode": "code",
          "exemplar": true,
          "expr": "logstash_stats_jvm_mem_pool_peak_max_bytes{pool='young',instance=~'$instance'}",
          "hide": false,
          "legendFormat": "young_pool_peak  ({{instance}})",
          "range": true,
          "refId": "C"
        },
        {
          "datasource": {
            "type": "prometheus",
            "uid": "${DS_PROMETHEUS}"
          },
          "editorMode": "code",
          "exemplar": true,
          "expr": "logstash_stats_jvm_mem_pool_peak_used_bytes{pool='young',instance=~'$instance'}",
          "hide": false,
          "legendFormat": "young_pool_peak_used ({{instance}})",
          "range": true,
          "refId": "D"
        },
        {
          "datasource": {
            "type": "prometheus",
            "uid": "${DS_PROMETHEUS}"
          },
          "editorMode": "code",
          "exemplar": true,
          "expr": "logstash_stats_jvm_mem_pool_peak_used_bytes{pool='young',instance=~'$instance'}",
          "hide": false,
          "legendFormat": "young_used ({{instance}})",
          "range": true,
          "refId": "E"
        }
      ],
      "title": "Young pool usage",
      "transparent": true,
      "type": "timeseries"
    },
    {
      "datasource": {
        "type": "prometheus",
        "uid": "${DS_PROMETHEUS}"
      },
      "fieldConfig": {
        "defaults": {
          "color": {
            "mode": "palette-classic"
          },
          "custom": {
            "axisBorderShow": false,
            "axisCenteredZero": false,
            "axisColorMode": "text",
            "axisLabel": "",
            "axisPlacement": "auto",
            "barAlignment": 0,
            "barWidthFactor": 0.6,
            "drawStyle": "line",
            "fillOpacity": 0,
            "gradientMode": "none",
            "hideFrom": {
              "legend": false,
              "tooltip": false,
              "viz": false
            },
            "insertNulls": false,
            "lineInterpolation": "linear",
            "lineWidth": 1,
            "pointSize": 5,
            "scaleDistribution": {
              "type": "linear"
            },
            "showPoints": "never",
            "spanNulls": false,
            "stacking": {
              "group": "A",
              "mode": "none"
            },
            "thresholdsStyle": {
              "mode": "off"
            }
          },
          "links": [],
          "mappings": [],
          "thresholds": {
            "mode": "absolute",
            "steps": [
              {
                "color": "green",
                "value": null
              },
              {
                "color": "red",
                "value": 80
              }
            ]
          },
          "unit": "decbytes"
        },
        "overrides": []
      },
      "gridPos": {
        "h": 6,
        "w": 8,
        "x": 8,
        "y": 67
      },
      "id": 2288,
      "options": {
        "legend": {
          "calcs": [],
          "displayMode": "list",
          "placement": "bottom",
          "showLegend": false
        },
        "tooltip": {
          "hideZeros": false,
          "maxHeight": 600,
          "mode": "multi",
          "sort": "none"
        }
      },
      "pluginVersion": "11.5.2",
      "targets": [
        {
          "datasource": {
            "type": "prometheus",
            "uid": "${DS_PROMETHEUS}"
          },
          "editorMode": "code",
          "expr": "logstash_stats_jvm_mem_pool_committed_bytes{pool='survivor',instance=~'$instance'}",
          "hide": false,
          "legendFormat": "{{instance}}-survivor_pool_committed",
          "range": true,
          "refId": "A"
        },
        {
          "datasource": {
            "type": "prometheus",
            "uid": "${DS_PROMETHEUS}"
          },
          "editorMode": "code",
          "expr": "logstash_stats_jvm_mem_pool_max_bytes{pool='survivor',instance=~'$instance'}",
          "legendFormat": "{{instance}}-survivor_pool_max",
          "range": true,
          "refId": "B"
        },
        {
          "datasource": {
            "type": "prometheus",
            "uid": "${DS_PROMETHEUS}"
          },
          "editorMode": "code",
          "expr": "logstash_stats_jvm_mem_pool_peak_max_bytes{pool='survivor',instance=~'$instance'}",
          "legendFormat": "{{instance}}-survivor_pool_peak_max",
          "range": true,
          "refId": "C"
        },
        {
          "datasource": {
            "type": "prometheus",
            "uid": "${DS_PROMETHEUS}"
          },
          "editorMode": "code",
          "expr": "logstash_stats_jvm_mem_pool_peak_used_bytes{pool='survivor',instance=~'$instance'}",
          "legendFormat": "{{instance}}-survivor_pool_peak_used",
          "range": true,
          "refId": "D"
        },
        {
          "datasource": {
            "type": "prometheus",
            "uid": "${DS_PROMETHEUS}"
          },
          "editorMode": "code",
          "expr": "logstash_stats_jvm_mem_pool_peak_used_bytes{pool='survivor',instance=~'$instance'}",
          "legendFormat": "{{instance}}-survivor_used",
          "range": true,
          "refId": "E"
        }
      ],
      "title": "Survivor pool usage",
      "transparent": true,
      "type": "timeseries"
    },
    {
      "datasource": {
        "type": "prometheus",
        "uid": "${DS_PROMETHEUS}"
      },
      "fieldConfig": {
        "defaults": {
          "color": {
            "mode": "palette-classic"
          },
          "custom": {
            "axisBorderShow": false,
            "axisCenteredZero": false,
            "axisColorMode": "text",
            "axisLabel": "",
            "axisPlacement": "auto",
            "barAlignment": 0,
            "barWidthFactor": 0.6,
            "drawStyle": "line",
            "fillOpacity": 0,
            "gradientMode": "none",
            "hideFrom": {
              "legend": false,
              "tooltip": false,
              "viz": false
            },
            "insertNulls": false,
            "lineInterpolation": "linear",
            "lineWidth": 1,
            "pointSize": 5,
            "scaleDistribution": {
              "type": "linear"
            },
            "showPoints": "never",
            "spanNulls": false,
            "stacking": {
              "group": "A",
              "mode": "none"
            },
            "thresholdsStyle": {
              "mode": "off"
            }
          },
          "links": [],
          "mappings": [],
          "thresholds": {
            "mode": "absolute",
            "steps": [
              {
                "color": "green",
                "value": null
              },
              {
                "color": "red",
                "value": 80
              }
            ]
          },
          "unit": "decbytes"
        },
        "overrides": []
      },
      "gridPos": {
        "h": 6,
        "w": 8,
        "x": 16,
        "y": 67
      },
      "id": 2286,
      "options": {
        "legend": {
          "calcs": [],
          "displayMode": "list",
          "placement": "bottom",
          "showLegend": false
        },
        "tooltip": {
          "hideZeros": false,
          "maxHeight": 600,
          "mode": "multi",
          "sort": "none"
        }
      },
      "pluginVersion": "11.5.2",
      "targets": [
        {
          "datasource": {
            "type": "prometheus",
            "uid": "${DS_PROMETHEUS}"
          },
          "editorMode": "code",
          "exemplar": true,
          "expr": "logstash_stats_jvm_mem_pool_committed_bytes{pool='old',instance=~'$instance'}",
          "legendFormat": "old_pool_committed ({{instance}})",
          "range": true,
          "refId": "A"
        },
        {
          "datasource": {
            "type": "prometheus",
            "uid": "${DS_PROMETHEUS}"
          },
          "editorMode": "code",
          "exemplar": true,
          "expr": "logstash_stats_jvm_mem_pool_max_bytes{pool='old',instance=~'$instance'}",
          "hide": false,
          "legendFormat": "old_pool_max ({{instance}})",
          "range": true,
          "refId": "B"
        },
        {
          "datasource": {
            "type": "prometheus",
            "uid": "${DS_PROMETHEUS}"
          },
          "editorMode": "code",
          "exemplar": true,
          "expr": "logstash_stats_jvm_mem_pool_peak_max_bytes{pool='old',instance=~'$instance'}",
          "hide": false,
          "legendFormat": "old_pool_peak_max ({{instance}})",
          "range": true,
          "refId": "C"
        },
        {
          "datasource": {
            "type": "prometheus",
            "uid": "${DS_PROMETHEUS}"
          },
          "editorMode": "code",
          "exemplar": true,
          "expr": "logstash_stats_jvm_mem_pool_peak_used_bytes{pool='old',instance=~'$instance'}",
          "hide": false,
          "legendFormat": "old_pool_peak_used ({{instance}})",
          "range": true,
          "refId": "D"
        },
        {
          "datasource": {
            "type": "prometheus",
            "uid": "${DS_PROMETHEUS}"
          },
          "editorMode": "code",
          "exemplar": true,
          "expr": "logstash_stats_jvm_mem_pool_peak_used_bytes{pool='old',instance=~'$instance'}",
          "hide": false,
          "legendFormat": "old_used ({{instance}})",
          "range": true,
          "refId": "E"
        }
      ],
      "title": "Old pool usage",
      "transparent": true,
      "type": "timeseries"
    },
    {
      "collapsed": false,
      "gridPos": {
        "h": 1,
        "w": 24,
        "x": 0,
        "y": 73
      },
      "id": 2639,
      "panels": [],
      "title": "Pipeline",
      "type": "row"
    },
    {
      "datasource": {
        "type": "prometheus",
        "uid": "${DS_PROMETHEUS}"
      },
      "fieldConfig": {
        "defaults": {
          "color": {
            "mode": "palette-classic"
          },
          "custom": {
            "axisBorderShow": false,
            "axisCenteredZero": false,
            "axisColorMode": "text",
            "axisLabel": "",
            "axisPlacement": "auto",
            "barAlignment": 0,
            "drawStyle": "line",
            "fillOpacity": 10,
            "gradientMode": "none",
            "hideFrom": {
              "legend": false,
              "tooltip": false,
              "viz": false
            },
            "insertNulls": false,
            "lineInterpolation": "linear",
            "lineWidth": 1,
            "pointSize": 5,
            "scaleDistribution": {
              "type": "linear"
            },
            "showPoints": "never",
            "spanNulls": true,
            "stacking": {
              "group": "A",
              "mode": "none"
            },
            "thresholdsStyle": {
              "mode": "off"
            }
          },
          "links": [],
          "mappings": [],
          "thresholds": {
            "mode": "absolute",
            "steps": [
              {
                "color": "green",
                "value": null
              },
              {
                "color": "red",
                "value": 80
              }
            ]
          },
          "unit": "ms"
        },
        "overrides": []
      },
      "gridPos": {
        "h": 6,
        "w": 24,
        "x": 0,
        "y": 74
      },
      "id": 2641,
      "options": {
        "legend": {
          "calcs": [],
          "displayMode": "table",
          "placement": "right",
          "showLegend": true
        },
        "tooltip": {
          "maxHeight": 600,
          "mode": "multi",
          "sort": "none"
        }
      },
      "pluginVersion": "11.5.2",
      "repeat": "pod",
      "repeatDirection": "h",
      "targets": [
        {
          "datasource": {
            "type": "prometheus",
            "uid": "${DS_PROMETHEUS}"
          },
          "editorMode": "code",
          "exemplar": true,
          "expr": "avg(irate(logstash_stats_pipeline_events_queue_push_duration{instance=~'$instance'}[$__range])/irate(logstash_stats_pipeline_events_in{instance=~'$instance'}[$__range])) by (instance, pipeline)",
          "hide": false,
          "legendFormat": "avg waiting time ({{pipeline}})",
          "range": true,
          "refId": "A"
        },
        {
          "datasource": {
            "type": "prometheus",
            "uid": "${DS_PROMETHEUS}"
          },
          "editorMode": "code",
          "exemplar": true,
          "expr": "avg(irate(logstash_stats_pipeline_events_duration{instance=~'$instance'}[$__range])/irate(logstash_stats_pipeline_events_out{instance=~'$instance'}[$__range])) by (instance, pipeline)",
          "hide": false,
          "legendFormat": "avg process time  ({{pipeline}})",
          "range": true,
          "refId": "B"
        }
      ],
      "title": "$instance - Events processing times",
      "transparent": true,
      "type": "timeseries"
    },
    {
      "datasource": {
        "type": "prometheus",
        "uid": "${DS_PROMETHEUS}"
      },
      "description": "Documents in Queue",
      "fieldConfig": {
        "defaults": {
          "color": {
            "mode": "palette-classic"
          },
          "custom": {
            "axisBorderShow": false,
            "axisCenteredZero": false,
            "axisColorMode": "text",
            "axisLabel": "",
            "axisPlacement": "auto",
            "barAlignment": 0,
            "drawStyle": "line",
            "fillOpacity": 0,
            "gradientMode": "none",
            "hideFrom": {
              "legend": false,
              "tooltip": false,
              "viz": false
            },
            "insertNulls": false,
            "lineInterpolation": "linear",
            "lineWidth": 1,
            "pointSize": 5,
            "scaleDistribution": {
              "type": "linear"
            },
            "showPoints": "auto",
            "spanNulls": false,
            "stacking": {
              "group": "A",
              "mode": "none"
            },
            "thresholdsStyle": {
              "mode": "off"
            }
          },
          "mappings": [],
          "thresholds": {
            "mode": "absolute",
            "steps": [
              {
                "color": "green",
                "value": null
              },
              {
                "color": "red",
                "value": 80
              }
            ]
          }
        },
        "overrides": []
      },
      "gridPos": {
        "h": 7,
        "w": 24,
        "x": 0,
        "y": 80
      },
      "id": 6954,
      "options": {
        "legend": {
          "calcs": [
            "lastNotNull"
          ],
          "displayMode": "table",
          "placement": "right",
          "showLegend": true
        },
        "tooltip": {
          "maxHeight": 600,
          "mode": "single",
          "sort": "none"
        }
      },
      "repeat": "pod",
      "repeatDirection": "h",
      "targets": [
        {
          "datasource": {
            "type": "prometheus",
            "uid": "${DS_PROMETHEUS}"
          },
          "editorMode": "code",
          "exemplar": true,
          "expr": "logstash_stats_pipeline_queue_events_count{instance=~'$instance',pipeline=~'$pipeline'}",
          "legendFormat": "{{pipeline}}",
          "range": true,
          "refId": "A"
        }
      ],
      "title": "Pipeline Queue Size ($pipeline)",
      "type": "timeseries"
    },
    {
      "collapsed": false,
      "gridPos": {
        "h": 1,
        "w": 24,
        "x": 0,
        "y": 87
      },
      "id": 6761,
      "panels": [],
      "title": "Pipeline Inputs",
      "type": "row"
    },
    {
      "datasource": {
        "type": "prometheus",
        "uid": "${DS_PROMETHEUS}"
      },
      "description": "",
      "fieldConfig": {
        "defaults": {
          "color": {
            "mode": "palette-classic"
          },
          "custom": {
            "axisBorderShow": false,
            "axisCenteredZero": false,
            "axisColorMode": "text",
            "axisLabel": "",
            "axisPlacement": "auto",
            "barAlignment": 0,
            "drawStyle": "line",
            "fillOpacity": 10,
            "gradientMode": "none",
            "hideFrom": {
              "legend": false,
              "tooltip": false,
              "viz": false
            },
            "insertNulls": false,
            "lineInterpolation": "linear",
            "lineWidth": 1,
            "pointSize": 5,
            "scaleDistribution": {
              "type": "linear"
            },
            "showPoints": "never",
            "spanNulls": false,
            "stacking": {
              "group": "A",
              "mode": "none"
            },
            "thresholdsStyle": {
              "mode": "off"
            }
          },
          "links": [],
          "mappings": [],
          "thresholds": {
            "mode": "absolute",
            "steps": [
              {
                "color": "green",
                "value": null
              },
              {
                "color": "red",
                "value": 80
              }
            ]
          },
          "unit": "short"
        },
        "overrides": []
      },
      "gridPos": {
        "h": 7,
        "w": 24,
        "x": 0,
        "y": 88
      },
      "hideTimeOverride": false,
      "id": 5934,
      "options": {
        "legend": {
          "calcs": [
            "lastNotNull",
            "max"
          ],
          "displayMode": "table",
          "placement": "right",
          "showLegend": true
        },
        "tooltip": {
          "maxHeight": 600,
          "mode": "multi",
          "sort": "none"
        }
      },
      "pluginVersion": "11.5.2",
      "repeat": "pod",
      "repeatDirection": "h",
      "targets": [
        {
          "datasource": {
            "type": "prometheus",
            "uid": "${DS_PROMETHEUS}"
          },
          "editorMode": "code",
          "expr": "sum by (job) (irate(logstash_stats_pipeline_events_in{instance=~'$instance'}[$__range]))",
          "legendFormat": "total",
          "range": true,
          "refId": "A"
        }
      ],
      "timeFrom": "1h",
      "title": "Pipeline Input events / sec over the last hour ($instance)",
      "transparent": true,
      "type": "timeseries"
    },
    {
      "datasource": {
        "type": "prometheus",
        "uid": "${DS_PROMETHEUS}"
      },
      "fieldConfig": {
        "defaults": {
          "color": {
            "mode": "palette-classic"
          },
          "custom": {
            "axisBorderShow": false,
            "axisCenteredZero": false,
            "axisColorMode": "text",
            "axisLabel": "",
            "axisPlacement": "auto",
            "barAlignment": 0,
            "drawStyle": "line",
            "fillOpacity": 0,
            "gradientMode": "none",
            "hideFrom": {
              "legend": false,
              "tooltip": false,
              "viz": false
            },
            "insertNulls": false,
            "lineInterpolation": "linear",
            "lineWidth": 1,
            "pointSize": 5,
            "scaleDistribution": {
              "type": "linear"
            },
            "showPoints": "never",
            "spanNulls": true,
            "stacking": {
              "group": "A",
              "mode": "none"
            },
            "thresholdsStyle": {
              "mode": "off"
            }
          },
          "links": [],
          "mappings": [],
          "thresholds": {
            "mode": "absolute",
            "steps": [
              {
                "color": "green",
                "value": null
              },
              {
                "color": "red",
                "value": 80
              }
            ]
          },
          "unit": "ms"
        },
        "overrides": []
      },
      "gridPos": {
        "h": 7,
        "w": 24,
        "x": 0,
        "y": 95
      },
      "id": 2978,
      "options": {
        "legend": {
          "calcs": [
            "lastNotNull"
          ],
          "displayMode": "list",
          "placement": "right",
          "showLegend": true
        },
        "tooltip": {
          "maxHeight": 600,
          "mode": "multi",
          "sort": "asc"
        }
      },
      "pluginVersion": "11.5.2",
      "repeat": "pod",
      "repeatDirection": "h",
      "targets": [
        {
          "datasource": {
            "type": "prometheus",
            "uid": "${DS_PROMETHEUS}"
          },
          "editorMode": "code",
          "exemplar": true,
          "expr": "max(increase(logstash_stats_pipeline_plugin_events_queue_push_duration{instance=~'$instance',pipeline=~\"$pipeline\",plugin=~'$input_plugin',plugin_type='input'}[$__range])*1000/increase(logstash_stats_pipeline_plugin_events_out{instance=~'$instance',pipeline=~\"$pipeline\",plugin=~'$input_plugin',plugin_type='input'}[$__range])) by (instance, pipeline, plugin)",
          "legendFormat": "queue wait: ({{pipeline}}::{{plugin}})",
          "range": true,
          "refId": "A"
        }
      ],
      "title": "Input plugins: Queue Push Waiting Times ($instance)",
      "transparent": true,
      "type": "timeseries"
    },
    {
      "collapsed": false,
      "gridPos": {
        "h": 1,
        "w": 24,
        "x": 0,
        "y": 102
      },
      "id": 6795,
      "panels": [],
      "title": "Pipeline Outputs ($pipeline)",
      "type": "row"
    },
    {
      "datasource": {
        "type": "prometheus",
        "uid": "${DS_PROMETHEUS}"
      },
      "description": "An \"output event\" is a 20MB \"bulk\" send in most cases",
      "fieldConfig": {
        "defaults": {
          "color": {
            "mode": "palette-classic"
          },
          "custom": {
            "axisBorderShow": false,
            "axisCenteredZero": false,
            "axisColorMode": "text",
            "axisLabel": "",
            "axisPlacement": "auto",
            "barAlignment": 0,
            "drawStyle": "line",
            "fillOpacity": 10,
            "gradientMode": "none",
            "hideFrom": {
              "legend": false,
              "tooltip": false,
              "viz": false
            },
            "insertNulls": false,
            "lineInterpolation": "linear",
            "lineWidth": 1,
            "pointSize": 5,
            "scaleDistribution": {
              "type": "linear"
            },
            "showPoints": "never",
            "spanNulls": true,
            "stacking": {
              "group": "A",
              "mode": "none"
            },
            "thresholdsStyle": {
              "mode": "off"
            }
          },
          "links": [],
          "mappings": [],
          "thresholds": {
            "mode": "absolute",
            "steps": [
              {
                "color": "green",
                "value": null
              },
              {
                "color": "red",
                "value": 80
              }
            ]
          },
          "unit": "short"
        },
        "overrides": []
      },
      "gridPos": {
        "h": 6,
        "w": 24,
        "x": 0,
        "y": 103
      },
      "id": 6745,
      "options": {
        "legend": {
          "calcs": [
            "sum"
          ],
          "displayMode": "table",
          "placement": "right",
          "showLegend": true
        },
        "tooltip": {
          "maxHeight": 600,
          "mode": "multi",
          "sort": "none"
        }
      },
      "pluginVersion": "11.5.2",
      "repeat": "pod",
      "repeatDirection": "h",
      "targets": [
        {
          "datasource": {
            "type": "prometheus",
            "uid": "${DS_PROMETHEUS}"
          },
          "editorMode": "code",
          "exemplar": false,
          "expr": "increase(logstash_stats_pipeline_plugin_events_out{instance=~'$instance',pipeline=~\"$pipeline\",plugin=~'$output_plugin',plugin_type='output'}[$__range])",
          "instant": false,
          "legendFormat": "{{instance}} ({{pipeline}}) [{{plugin}}]",
          "range": true,
          "refId": "A"
        }
      ],
      "title": "Output events ($instance) ($output_plugin)",
      "transparent": true,
      "type": "timeseries"
    },
    {
      "datasource": {
        "type": "prometheus",
        "uid": "${DS_PROMETHEUS}"
      },
      "description": "An \"output event\" is a 20MB \"bulk\" send in most cases",
      "fieldConfig": {
        "defaults": {
          "color": {
            "mode": "palette-classic"
          },
          "custom": {
            "axisBorderShow": false,
            "axisCenteredZero": false,
            "axisColorMode": "text",
            "axisLabel": "",
            "axisPlacement": "auto",
            "barAlignment": 0,
            "drawStyle": "line",
            "fillOpacity": 10,
            "gradientMode": "none",
            "hideFrom": {
              "legend": false,
              "tooltip": false,
              "viz": false
            },
            "insertNulls": false,
            "lineInterpolation": "linear",
            "lineWidth": 1,
            "pointSize": 5,
            "scaleDistribution": {
              "type": "linear"
            },
            "showPoints": "never",
            "spanNulls": false,
            "stacking": {
              "group": "A",
              "mode": "none"
            },
            "thresholdsStyle": {
              "mode": "off"
            }
          },
          "links": [],
          "mappings": [],
          "thresholds": {
            "mode": "absolute",
            "steps": [
              {
                "color": "green",
                "value": null
              },
              {
                "color": "red",
                "value": 80
              }
            ]
          },
          "unit": "short"
        },
        "overrides": []
      },
      "gridPos": {
        "h": 7,
        "w": 24,
        "x": 0,
        "y": 109
      },
      "hideTimeOverride": false,
      "id": 6098,
      "options": {
        "legend": {
          "calcs": [
            "lastNotNull",
            "max"
          ],
          "displayMode": "table",
          "placement": "right",
          "showLegend": true
        },
        "tooltip": {
          "maxHeight": 600,
          "mode": "multi",
          "sort": "none"
        }
      },
      "pluginVersion": "11.5.2",
      "repeat": "pod",
      "repeatDirection": "h",
      "targets": [
        {
          "datasource": {
            "type": "prometheus",
            "uid": "${DS_PROMETHEUS}"
          },
          "editorMode": "code",
          "exemplar": true,
          "expr": "sum by (job) (irate(logstash_stats_pipeline_plugin_events_out{instance=~'$instance',plugin_type='output'}[$__range]))",
          "legendFormat": "Total",
          "range": true,
          "refId": "A"
        }
      ],
      "timeFrom": "1h",
      "title": "Pipeline Output events / sec over the last hour ($instance)",
      "transparent": true,
      "type": "timeseries"
    },
    {
      "collapsed": false,
      "gridPos": {
        "h": 1,
        "w": 24,
        "x": 0,
        "y": 116
      },
      "id": 6813,
      "panels": [],
      "title": "Pipeline I/O Health ($pipeline)",
      "type": "row"
    },
    {
      "datasource": {
        "type": "prometheus",
        "uid": "${DS_PROMETHEUS}"
      },
      "description": "",
      "fieldConfig": {
        "defaults": {
          "color": {
            "mode": "palette-classic"
          },
          "custom": {
            "axisBorderShow": false,
            "axisCenteredZero": false,
            "axisColorMode": "text",
            "axisLabel": "",
            "axisPlacement": "auto",
            "barAlignment": 0,
            "drawStyle": "line",
            "fillOpacity": 10,
            "gradientMode": "none",
            "hideFrom": {
              "legend": false,
              "tooltip": false,
              "viz": false
            },
            "insertNulls": false,
            "lineInterpolation": "linear",
            "lineWidth": 1,
            "pointSize": 5,
            "scaleDistribution": {
              "type": "linear"
            },
            "showPoints": "never",
            "spanNulls": true,
            "stacking": {
              "group": "A",
              "mode": "none"
            },
            "thresholdsStyle": {
              "mode": "off"
            }
          },
          "links": [],
          "mappings": [],
          "thresholds": {
            "mode": "absolute",
            "steps": [
              {
                "color": "green",
                "value": null
              },
              {
                "color": "red",
                "value": 80
              }
            ]
          },
          "unit": "iops"
        },
        "overrides": []
      },
      "gridPos": {
        "h": 6,
        "w": 24,
        "x": 0,
        "y": 117
      },
      "id": 2817,
      "options": {
        "legend": {
          "calcs": [
            "lastNotNull",
            "max"
          ],
          "displayMode": "table",
          "placement": "right",
          "showLegend": true
        },
        "tooltip": {
          "maxHeight": 600,
          "mode": "multi",
          "sort": "none"
        }
      },
      "pluginVersion": "11.5.2",
      "repeat": "pod",
      "repeatDirection": "h",
      "targets": [
        {
          "datasource": {
            "type": "prometheus",
            "uid": "${DS_PROMETHEUS}"
          },
          "editorMode": "code",
          "expr": "avg((irate(logstash_stats_pipeline_events_out{instance=~'$instance',pipeline=~\"$pipeline\"}[$__range])/irate(logstash_stats_pipeline_events_duration{instance=~'$instance',pipeline=~\"$pipeline\"}[$__range]))*1000) by (instance, pipeline)",
          "hide": false,
          "legendFormat": "Overall Rate for {{instance}} ({{pipeline}})",
          "range": true,
          "refId": "B"
        },
        {
          "datasource": {
            "type": "prometheus",
            "uid": "${DS_PROMETHEUS}"
          },
          "editorMode": "code",
          "exemplar": true,
          "expr": "avg((irate(logstash_stats_pipeline_plugin_events_out{instance=~'$instance',pipeline=~\"$pipeline\",plugin_type='output'}[$__range])/irate(logstash_stats_pipeline_plugin_events_duration{instance=~'$instance',pipeline=~\"$pipeline\",plugin_type='output'}[$__range])*1000) < 100000) by (instance, pipeline)",
          "legendFormat": "Outputs Rate for {{instance}} ({{pipeline}})",
          "range": true,
          "refId": "A"
        },
        {
          "datasource": {
            "type": "prometheus",
            "uid": "${DS_PROMETHEUS}"
          },
          "editorMode": "code",
          "exemplar": true,
          "expr": "avg((irate(logstash_stats_pipeline_queue_events_count{instance=~'$instance',pipeline=~\"$pipeline\",plugin_type='input'}[$__range])/irate(logstash_stats_pipeline_events_queue_push_duration{instance=~'$instance',pipeline=~\"$pipeline\",plugin_type='input'}[$__range]))*1000) by (instance, pipeline)",
          "hide": false,
          "legendFormat": "Input Queue Pressure for {{instance}} ({{pipeline}})",
          "range": true,
          "refId": "C"
        }
      ],
      "title": "Processed Events I/O Rate ($instance)  (events/sec)",
      "transparent": true,
      "type": "timeseries"
    }
  ],
  "preload": false,
  "refresh": "5s",
  "schemaVersion": 40,
  "tags": [],
  "templating": {
    "list": [
      {
        "current": {
          "text": "${VAR_CPU_THRESHOLD}",
          "value": "${VAR_CPU_THRESHOLD}"
        },
        "description": "Number of cores or K8s CPU limit (Used as load threshold line)",
        "hide": 2,
        "label": "CPU Threshold",
        "name": "cpu_threshold",
        "query": "${VAR_CPU_THRESHOLD}",
        "skipUrlSync": true,
        "type": "constant"
      },
      {
        "current": {
          "text": "10.41.0.137:9198",
          "value": "10.41.0.137:9198"
        },
        "datasource": {
          "type": "prometheus",
          "uid": "${DS_PROMETHEUS}"
        },
        "definition": "label_values(logstash_info_node,instance)",
        "includeAll": false,
        "label": "Instance",
        "name": "instance",
        "options": [],
        "query": {
          "qryType": 1,
          "query": "label_values(logstash_info_node,instance)",
          "refId": "PrometheusVariableQueryEditor-VariableQuery"
        },
        "refresh": 1,
        "regex": "",
        "type": "query"
      },
      {
        "current": {
          "text": "aiops_anomaly_detection",
          "value": "aiops_anomaly_detection"
        },
        "datasource": {
          "type": "prometheus",
          "uid": "${DS_PROMETHEUS}"
        },
        "definition": "label_values(logstash_stats_pipeline_events_in{instance=~\"$instance\"},pipeline)",
        "description": "Logstash Pipeline",
        "includeAll": false,
        "label": "Logstash Pipeline",
        "name": "pipeline",
        "options": [],
        "query": {
          "qryType": 1,
          "query": "label_values(logstash_stats_pipeline_events_in{instance=~\"$instance\"},pipeline)",
          "refId": "PrometheusVariableQueryEditor-VariableQuery"
        },
        "refresh": 1,
        "regex": "",
        "type": "query"
      },
      {
        "current": {
          "text": "kafka",
          "value": "kafka"
        },
        "datasource": {
          "type": "prometheus",
          "uid": "${DS_PROMETHEUS}"
        },
        "definition": "label_values(logstash_stats_pipeline_plugin_events_out{instance=~\"$instance\", plugin_type=\"input\"},plugin)",
        "includeAll": false,
        "name": "input_plugin",
        "options": [],
        "query": {
          "qryType": 1,
          "query": "label_values(logstash_stats_pipeline_plugin_events_out{instance=~\"$instance\", plugin_type=\"input\"},plugin)",
          "refId": "PrometheusVariableQueryEditor-VariableQuery"
        },
        "refresh": 1,
        "regex": "",
        "type": "query"
      },
      {
        "current": {
          "text": "mutate",
          "value": "mutate"
        },
        "datasource": {
          "type": "prometheus",
          "uid": "${DS_PROMETHEUS}"
        },
        "definition": "label_values(logstash_stats_pipeline_plugin_events_out{instance=~\"$instance\", plugin_type=\"filter\"},plugin)",
        "includeAll": false,
        "name": "filter_plugin",
        "options": [],
        "query": {
          "qryType": 1,
          "query": "label_values(logstash_stats_pipeline_plugin_events_out{instance=~\"$instance\", plugin_type=\"filter\"},plugin)",
          "refId": "PrometheusVariableQueryEditor-VariableQuery"
        },
        "refresh": 1,
        "regex": "",
        "type": "query"
      },
      {
        "current": {
          "text": "http",
          "value": "http"
        },
        "datasource": {
          "type": "prometheus",
          "uid": "${DS_PROMETHEUS}"
        },
        "definition": "label_values(logstash_stats_pipeline_plugin_events_out{instance=~\"$instance\", plugin_type=\"output\"},plugin)",
        "includeAll": false,
        "name": "output_plugin",
        "options": [],
        "query": {
          "qryType": 1,
          "query": "label_values(logstash_stats_pipeline_plugin_events_out{instance=~\"$instance\", plugin_type=\"output\"},plugin)",
          "refId": "PrometheusVariableQueryEditor-VariableQuery"
        },
        "refresh": 1,
        "regex": "",
        "type": "query"
      },
      {
        "current": {
          "text": "codec:decode",
          "value": "codec:decode"
        },
        "datasource": {
          "type": "prometheus",
          "uid": "${DS_PROMETHEUS}"
        },
        "definition": "label_values(logstash_stats_pipeline_plugin_events_out{instance=~\"$instance\"},plugin_type)",
        "description": "Pipeline Plugin Type",
        "includeAll": false,
        "label": "Plugin Type",
        "name": "plugin_type",
        "options": [],
        "query": {
          "qryType": 1,
          "query": "label_values(logstash_stats_pipeline_plugin_events_out{instance=~\"$instance\"},plugin_type)",
          "refId": "PrometheusVariableQueryEditor-VariableQuery"
        },
        "refresh": 1,
        "regex": "",
        "type": "query"
      },
      {
        "current": {
          "text": "VictoriaMetrics",
          "value": "prometheus"
        },
        "includeAll": false,
        "label": "Data Source",
        "name": "DS_PROMETHEUS",
        "options": [],
        "query": "prometheus",
        "refresh": 1,
        "regex": "",
        "type": "datasource"
      }
    ]
  },
  "time": {
    "from": "now-15m",
    "to": "now"
  },
  "timepicker": {},
  "timezone": "",
  "title": "Logstash",
  "uid": "fdy9m1ui16mf4a",
  "version": 1,
  "weekStart": ""
}